action_serializer/__init__.py
action_serializer/sample_group_viewset.py
action_serializer/serializers.py
action_serializer/settings.py
action_serializer/tests.py
action_serializer/urls.py
drf_action_serializer-1.0.5.dist-info/LICENSE
drf_action_serializer-1.0.5.dist-info/METADATA
drf_action_serializer-1.0.5.dist-info/WHEEL
drf_action_serializer-1.0.5.dist-info/top_level.txt
drf_action_serializer-1.0.5.dist-info/RECORD
