Metadata-Version: 1.1
Name: drf-action-serializer
Version: 1.0.5
Summary: A serializer that handles field configuration with multiple actions from ViewSets.
Home-page: https://github.com/gregschmit/drf-action-serializer
Author: Gregory N. Schmit
Author-email: schmitgreg@gmail.com
License: MIT
Platform: UNKNOWN
Classifier: Environment :: Web Environment
Classifier: Framework :: Django
Classifier: Intended Audience :: Developers
Classifier: License :: OSI Approved :: MIT License
Classifier: Programming Language :: Python :: 3
